maneuverrecognition/__init__.py
maneuverrecognition/evaluation.py
maneuverrecognition/modelling.py
maneuverrecognition/preprocessing.py
maneuverRecognition-0.0.6.dist-info/LICENSE
maneuverRecognition-0.0.6.dist-info/METADATA
maneuverRecognition-0.0.6.dist-info/WHEEL
maneuverRecognition-0.0.6.dist-info/top_level.txt
maneuverRecognition-0.0.6.dist-info/RECORD
